cs272_project/__init__.py
cs272_project/big_query_dataset.py
cs272_project/cli.py
cs272_project/fine_tuning.py
cs272_project/model.py
cs272_project/view_tanda_network.py
cs272_project/config/__init__.py
cs272_project/config/config.ini
cs272_project/config/config.py
cs272_project-0.2.0.dist-info/AUTHORS.rst
cs272_project-0.2.0.dist-info/LICENSE
cs272_project-0.2.0.dist-info/METADATA
cs272_project-0.2.0.dist-info/WHEEL
cs272_project-0.2.0.dist-info/entry_points.txt
cs272_project-0.2.0.dist-info/top_level.txt
cs272_project-0.2.0.dist-info/RECORD
