Metadata-Version: 2.1
Name: cs272-project
Version: 0.2.0
Summary: NLP Final Project
Home-page: https://github.com/taoyilee/cs272_project
Author: Michael Tao-Yi Lee
Author-email: taoyil@uci.edu
License: MIT license
Keywords: cs272_project
Platform: UNKNOWN
Classifier: Development Status :: 2 - Pre-Alpha
Classifier: Intended Audience :: Developers
Classifier: License :: OSI Approved :: MIT License
Classifier: Natural Language :: English
Classifier: Programming Language :: Python :: 3
Classifier: Programming Language :: Python :: 3.5
Classifier: Programming Language :: Python :: 3.6
Classifier: Programming Language :: Python :: 3.7
Classifier: Programming Language :: Python :: 3.8
Requires-Python: >=3.5
Requires-Dist: Click (>=7.0)
Requires-Dist: torch (==1.4.0)
Requires-Dist: transformers (==2.4.1)
Requires-Dist: youtokentome (==1.0.6)
Requires-Dist: tqdm (==4.42.1)
Requires-Dist: configobj (==5.0.6)
Requires-Dist: tensorboard (==2.1.0)
Requires-Dist: google-cloud-bigquery (==1.24.0)
Requires-Dist: pandas (==1.0.1)
